perlib/__init__.py
perlib/forecaster.py
perlib/analysis/__init__.py
perlib/analysis/exceptions.py
perlib/analysis/multivariate.py
perlib/analysis/plotting.py
perlib/analysis/univariate.py
perlib/analysis/validate.py
perlib/api/__init__.py
perlib/api/api.py
perlib/core/__init__.py
perlib/core/_requests.py
perlib/core/req_utils.py
perlib/core/tester.py
perlib/core/train.py
perlib/core/HyperOptimization/__init__.py
perlib/core/metrics/__init__.py
perlib/core/metrics/classification.py
perlib/core/metrics/regression.py
perlib/core/modelSelection/__init__.py
perlib/core/modelSelection/selection.py
perlib/core/models/__init__.py
perlib/core/models/dmodels.py
perlib/core/models/elm.py
perlib/core/models/lstnet.py
perlib/core/models/mmodels.py
perlib/core/models/prophet.py
perlib/core/models/smodels.py
perlib/core/optimizers/Optimizers.py
perlib/core/optimizers/__init__.py
perlib/datasets/__init__.py
perlib/datasets/airpassengers.py
perlib/datasets/ausbeer.py
perlib/datasets/austres.py
perlib/datasets/heartrate.py
perlib/datasets/lynx.py
perlib/datasets/taylor.py
perlib/datasets/wineind.py
perlib/datasets/woolyrnq.py
perlib/dbcon/__init__.py
perlib/piplines/__init__.py
perlib/piplines/dpipline.py
perlib/piplines/mpipline.py
perlib/preprocessing/Normalizing.py
perlib/preprocessing/__init__.py
perlib/preprocessing/_split.py
perlib/preprocessing/autopreprocess.py
perlib/preprocessing/encode.py
perlib/preprocessing/imputer.py
perlib/preprocessing/outliers.py
perlib/preprocessing/preparate.py
perlib/preprocessing/_utils/__init__.py
perlib/preprocessing/_utils/dataframe.py
perlib/preprocessing/_utils/dataset_utils.py
perlib/preprocessing/_utils/timeseries_dataset.py
perlib/preprocessing/_utils/tools.py
perlib-3.0.7.dist-info/LICENSE.md
perlib-3.0.7.dist-info/METADATA
perlib-3.0.7.dist-info/WHEEL
perlib-3.0.7.dist-info/top_level.txt
perlib-3.0.7.dist-info/RECORD
