Metadata-Version: 2.1
Name: perlib
Version: 3.0.7
Summary: Deep learning, Machine learning and Statistical learning for humans.
Home-page: https://github.com/Ruzzg/perlib
Author: Rüzgar Ersin Kanar
Author-email: ruzgarknr@gmail.com
License: Apache Software License
Keywords: perlib,tensorflow,machine learning,deep learning,statistical learning,automl,autodl,modelselection
Classifier: License :: OSI Approved :: Apache Software License
Classifier: Programming Language :: Python :: 3.9
Classifier: Programming Language :: Python :: 3.10
License-File: LICENSE.md
Requires-Dist: openpyxl
Requires-Dist: joblib
Requires-Dist: keras
Requires-Dist: keras_tcn
Requires-Dist: lightgbm
Requires-Dist: loguru
Requires-Dist: matplotlib
Requires-Dist: numpy
Requires-Dist: pandas
Requires-Dist: python_dateutil
Requires-Dist: scikit_learn
Requires-Dist: scipy
Requires-Dist: statsmodels
Requires-Dist: tensorflow
Requires-Dist: tqdm
Requires-Dist: xgboost
Requires-Dist: hpelm
Requires-Dist: catboost
Requires-Dist: Flask
Requires-Dist: prophet
